deephaven/plot/express/__init__.py
deephaven/plot/express/_register.py
deephaven/plot/express/_js/LICENSE
deephaven/plot/express/_js/package.json
deephaven/plot/express/_js/dist/DashboardPlugin.d.ts
deephaven/plot/express/_js/dist/DashboardPlugin.d.ts.map
deephaven/plot/express/_js/dist/DashboardPlugin.js
deephaven/plot/express/_js/dist/DashboardPlugin.js.map
deephaven/plot/express/_js/dist/PlotlyExpressChart.d.ts
deephaven/plot/express/_js/dist/PlotlyExpressChart.d.ts.map
deephaven/plot/express/_js/dist/PlotlyExpressChart.js
deephaven/plot/express/_js/dist/PlotlyExpressChart.js.map
deephaven/plot/express/_js/dist/PlotlyExpressChartModel.d.ts
deephaven/plot/express/_js/dist/PlotlyExpressChartModel.d.ts.map
deephaven/plot/express/_js/dist/PlotlyExpressChartModel.js
deephaven/plot/express/_js/dist/PlotlyExpressChartModel.js.map
deephaven/plot/express/_js/dist/PlotlyExpressChartPanel.d.ts
deephaven/plot/express/_js/dist/PlotlyExpressChartPanel.d.ts.map
deephaven/plot/express/_js/dist/PlotlyExpressChartPanel.js
deephaven/plot/express/_js/dist/PlotlyExpressChartPanel.js.map
deephaven/plot/express/_js/dist/PlotlyExpressChartUtils.d.ts
deephaven/plot/express/_js/dist/PlotlyExpressChartUtils.d.ts.map
deephaven/plot/express/_js/dist/PlotlyExpressChartUtils.js
deephaven/plot/express/_js/dist/PlotlyExpressChartUtils.js.map
deephaven/plot/express/_js/dist/PlotlyExpressPlugin.d.ts
deephaven/plot/express/_js/dist/PlotlyExpressPlugin.d.ts.map
deephaven/plot/express/_js/dist/PlotlyExpressPlugin.js
deephaven/plot/express/_js/dist/PlotlyExpressPlugin.js.map
deephaven/plot/express/_js/dist/index.d.ts
deephaven/plot/express/_js/dist/index.d.ts.map
deephaven/plot/express/_js/dist/index.js
deephaven/plot/express/_js/dist/index.js.map
deephaven/plot/express/_js/dist/useHandleSceneTicks.d.ts
deephaven/plot/express/_js/dist/useHandleSceneTicks.d.ts.map
deephaven/plot/express/_js/dist/useHandleSceneTicks.js
deephaven/plot/express/_js/dist/useHandleSceneTicks.js.map
deephaven_plugin_plotly_express-0.18.1.dist-info/licenses/LICENSE
deephaven_plugin_plotly_express-0.18.1.dist-info/METADATA
deephaven_plugin_plotly_express-0.18.1.dist-info/WHEEL
deephaven_plugin_plotly_express-0.18.1.dist-info/entry_points.txt
deephaven_plugin_plotly_express-0.18.1.dist-info/top_level.txt
deephaven_plugin_plotly_express-0.18.1.dist-info/RECORD
