Metadata-Version: 2.4
Name: deephaven-plugin-plotly-express
Version: 0.18.1
Summary: Deephaven Chart Plugin
Home-page: https://github.com/deephaven/deephaven-plugins
Author: Devin Smith, Vlad Babich, Joe Numainville
Author-email: josephnumainville@deephaven.io
Project-URL: Source Code, https://github.com/deephaven/deephaven-plugins
Project-URL: Bug Tracker, https://github.com/deephaven/deephaven-plugins/issues
Keywords: deephaven,plugin,graph
Platform: any
Classifier: Programming Language :: Python :: 3
Classifier: License :: OSI Approved :: Apache Software License
Classifier: Operating System :: OS Independent
Classifier: Environment :: Plugins
Classifier: Topic :: Scientific/Engineering :: Visualization
Classifier: Development Status :: 3 - Alpha
License-File: LICENSE
Requires-Dist: deephaven-core>=0.37.6
Requires-Dist: deephaven-plugin>=0.6.0
Requires-Dist: plotly<7.0.0,>=6.0.0
Requires-Dist: deephaven-plugin-utilities>=0.0.2
Requires-Dist: typing_extensions; python_version < "3.11"
Requires-Dist: jpy
Provides-Extra: all
Requires-Dist: kaleido<1.0.0; extra == "all"
Dynamic: license-file
